missdat/__init__.py
missdat/em_fiml.py
missdat/mcar_test.py
missdat/miss_diagnostics.py
missdat-0.1.8.dist-info/licenses/LICENSE.txt
missdat-0.1.8.dist-info/METADATA
missdat-0.1.8.dist-info/WHEEL
missdat-0.1.8.dist-info/top_level.txt
missdat-0.1.8.dist-info/RECORD
