Metadata-Version: 2.4
Name: missdat
Version: 0.1.8
Summary: A package for missing data diagnostics and estimating missing values
Author-email: "Drew E. Winters, PhD." <drewEwinters@gmail.com>
License: MIT
Project-URL: Homepage, https://github.com/drewwint/missdat
License-File: LICENSE.txt
Requires-Dist: numpy
Requires-Dist: pandas
Requires-Dist: scipy
Dynamic: license-file
